[{"id":4977698,"title":"Clear Thinking","userName":"MistyAamen","numViews":9,"numVotes":1,"numComments":0,"numHearts":0,"rank":0,"dateCreated":"2026-03-22 01:11:38","colors":["7A1E91","3BBFBC","CFDB35","B16052","8A2A3D"],"description":"","url":"http:\/\/www.colourlovers.com\/palette\/4977698\/Clear_Thinking","imageUrl":"http:\/\/www.colourlovers.com\/paletteImg\/7A1E91\/3BBFBC\/CFDB35\/B16052\/8A2A3D\/Clear_Thinking.png","badgeUrl":"http:\/\/www.colourlovers.com\/images\/badges\/pw\/4977\/4977698_Clear_Thinking.png","apiUrl":"http:\/\/www.colourlovers.com\/api\/palette\/4977698"}]
